agent_runtime_core/__init__.py
agent_runtime_core/config.py
agent_runtime_core/interfaces.py
agent_runtime_core/registry.py
agent_runtime_core/runner.py
agent_runtime_core/steps.py
agent_runtime_core/testing.py
agent_runtime_core/tool_calling_agent.py
agent_runtime_core/events/__init__.py
agent_runtime_core/events/base.py
agent_runtime_core/events/memory.py
agent_runtime_core/events/redis.py
agent_runtime_core/events/sqlite.py
agent_runtime_core/llm/__init__.py
agent_runtime_core/llm/anthropic.py
agent_runtime_core/llm/litellm_client.py
agent_runtime_core/llm/openai.py
agent_runtime_core/persistence/__init__.py
agent_runtime_core/persistence/base.py
agent_runtime_core/persistence/file.py
agent_runtime_core/persistence/manager.py
agent_runtime_core/queue/__init__.py
agent_runtime_core/queue/base.py
agent_runtime_core/queue/memory.py
agent_runtime_core/queue/redis.py
agent_runtime_core/queue/sqlite.py
agent_runtime_core/state/__init__.py
agent_runtime_core/state/base.py
agent_runtime_core/state/memory.py
agent_runtime_core/state/redis.py
agent_runtime_core/state/sqlite.py
agent_runtime_core/tracing/__init__.py
agent_runtime_core/tracing/langfuse.py
agent_runtime_core/tracing/noop.py
agent_runtime_core-0.5.2.dist-info/METADATA
agent_runtime_core-0.5.2.dist-info/WHEEL
agent_runtime_core-0.5.2.dist-info/licenses/LICENSE
agent_runtime_core-0.5.2.dist-info/RECORD
