Metadata-Version: 2.4
Name: agent-runtime-core
Version: 0.5.2
Summary: Framework-agnostic Python library for executing AI agents with consistent patterns
Project-URL: Homepage, https://github.com/makemore/agent-runtime-core
Project-URL: Repository, https://github.com/makemore/agent-runtime-core
Author: Chris Barry
License-Expression: MIT
License-File: LICENSE
Keywords: agents,ai,async,llm,runtime
Classifier: Development Status :: 3 - Alpha
Classifier: Intended Audience :: Developers
Classifier: License :: OSI Approved :: MIT License
Classifier: Programming Language :: Python :: 3
Classifier: Programming Language :: Python :: 3.11
Classifier: Programming Language :: Python :: 3.12
Classifier: Topic :: Scientific/Engineering :: Artificial Intelligence
Classifier: Topic :: Software Development :: Libraries :: Python Modules
Requires-Python: >=3.11
Provides-Extra: all
Requires-Dist: anthropic>=0.18.0; extra == 'all'
Requires-Dist: langfuse>=2.0.0; extra == 'all'
Requires-Dist: litellm>=1.0.0; extra == 'all'
Requires-Dist: openai>=1.0.0; extra == 'all'
Requires-Dist: redis>=5.0.0; extra == 'all'
Provides-Extra: anthropic
Requires-Dist: anthropic>=0.18.0; extra == 'anthropic'
Provides-Extra: dev
Requires-Dist: mypy>=1.0.0; extra == 'dev'
Requires-Dist: pytest-asyncio>=0.23.0; extra == 'dev'
Requires-Dist: pytest-cov>=4.0.0; extra == 'dev'
Requires-Dist: pytest>=8.0.0; extra == 'dev'
Requires-Dist: ruff>=0.1.0; extra == 'dev'
Provides-Extra: langfuse
Requires-Dist: langfuse>=2.0.0; extra == 'langfuse'
Provides-Extra: litellm
Requires-Dist: litellm>=1.0.0; extra == 'litellm'
Provides-Extra: openai
Requires-Dist: openai>=1.0.0; extra == 'openai'
Provides-Extra: redis
Requires-Dist: redis>=5.0.0; extra == 'redis'
